dynomock
