Metadata-Version: 1.1
Name: dynomock
Version: 0.2.0
Summary: endpoints mocker.
Home-page: https://github.com/vit0r/dynomock
Author: Vitor
Author-email: vitornascimentoaraujo@gmail.com
License: MIT
Platform: UNKNOWN
Classifier: Development Status :: 3 - Alpha
Classifier: License :: OSI Approved :: MIT License
Classifier: Operating System :: OS Independent
Classifier: Programming Language :: Python :: 3.6
